<?xml version="1.0" encoding="utf-8" ?>
<dwsync>
<file name="AlphaBar.png" server="ftp.agenciaewtec.com.br/sistema/" local="130969949520345163" remote="130946856000000000" Dst="2" />
<file name="Bars.png" server="ftp.agenciaewtec.com.br/sistema/" local="130969949520720430" remote="130946856000000000" Dst="2" />
<file name="NoColor.png" server="ftp.agenciaewtec.com.br/sistema/" local="130969949522676819" remote="130946856000000000" Dst="2" />
<file name="bar-opacity.png" server="ftp.agenciaewtec.com.br/sistema/" local="130969949522962023" remote="130946856000000000" Dst="2" />
<file name="Maps.png" server="ftp.agenciaewtec.com.br/sistema/" local="130969949523172172" remote="130946856000000000" Dst="2" />
<file name="Thumbs.db" server="ftp.agenciaewtec.com.br/sistema/" local="130969949523587472" remote="130946856000000000" Dst="2" />
<file name="map-opacity.png" server="ftp.agenciaewtec.com.br/sistema/" local="130969949524368028" remote="130946856000000000" Dst="2" />
<file name="mappoint.gif" server="ftp.agenciaewtec.com.br/sistema/" local="130969949524663239" remote="130946856000000000" Dst="2" />
<file name="picker.gif" server="ftp.agenciaewtec.com.br/sistema/" local="130969949524968456" remote="130946856000000000" Dst="2" />
<file name="preview-opacity.png" server="ftp.agenciaewtec.com.br/sistema/" local="130969949525288689" remote="130946856000000000" Dst="2" />
<file name="rangearrows.gif" server="ftp.agenciaewtec.com.br/sistema/" local="130969949526309412" remote="130946856000000000" Dst="2" />
<file name="AlphaBar.png" server="ftp.ewebtecnologia.com.br/megasena/" local="130969949520000000" remote="130972801200000000" Dst="2" />
<file name="bar-opacity.png" server="ftp.ewebtecnologia.com.br/megasena/" local="130969949520000000" remote="130972801200000000" Dst="2" />
<file name="Bars.png" server="ftp.ewebtecnologia.com.br/megasena/" local="130969949520000000" remote="130972801200000000" Dst="2" />
<file name="map-opacity.png" server="ftp.ewebtecnologia.com.br/megasena/" local="130969949520000000" remote="130972801200000000" Dst="2" />
<file name="mappoint.gif" server="ftp.ewebtecnologia.com.br/megasena/" local="130969949520000000" remote="130972801200000000" Dst="2" />
<file name="Maps.png" server="ftp.ewebtecnologia.com.br/megasena/" local="130969949520000000" remote="130972801200000000" Dst="2" />
<file name="NoColor.png" server="ftp.ewebtecnologia.com.br/megasena/" local="130969949520000000" remote="130972801200000000" Dst="2" />
<file name="picker.gif" server="ftp.ewebtecnologia.com.br/megasena/" local="130969949520000000" remote="130972801200000000" Dst="2" />
<file name="preview-opacity.png" server="ftp.ewebtecnologia.com.br/megasena/" local="130969949520000000" remote="130972801200000000" Dst="2" />
<file name="rangearrows.gif" server="ftp.ewebtecnologia.com.br/megasena/" local="130969949520000000" remote="130972801200000000" Dst="2" />
<file name="Thumbs.db" server="ftp.ewebtecnologia.com.br/megasena/" local="130969949523587472" remote="130972801200000000" Dst="2" />
<file name="AlphaBar.png" server="C:/xampp/htdocs/brasfoot/" local="130969949520000000" remote="130969949520000000" Dst="2" />
<file name="bar-opacity.png" server="C:/xampp/htdocs/brasfoot/" local="130969949520000000" remote="130969949520000000" Dst="2" />
<file name="Bars.png" server="C:/xampp/htdocs/brasfoot/" local="130969949520000000" remote="130969949520000000" Dst="2" />
<file name="map-opacity.png" server="C:/xampp/htdocs/brasfoot/" local="130969949520000000" remote="130969949520000000" Dst="2" />
<file name="mappoint.gif" server="C:/xampp/htdocs/brasfoot/" local="130969949520000000" remote="130969949520000000" Dst="2" />
<file name="Maps.png" server="C:/xampp/htdocs/brasfoot/" local="130969949520000000" remote="130969949520000000" Dst="2" />
<file name="NoColor.png" server="C:/xampp/htdocs/brasfoot/" local="130969949520000000" remote="130969949520000000" Dst="2" />
<file name="picker.gif" server="C:/xampp/htdocs/brasfoot/" local="130969949520000000" remote="130969949520000000" Dst="2" />
<file name="preview-opacity.png" server="C:/xampp/htdocs/brasfoot/" local="130969949520000000" remote="130969949520000000" Dst="2" />
<file name="rangearrows.gif" server="C:/xampp/htdocs/brasfoot/" local="130969949520000000" remote="130969949520000000" Dst="2" />
<file name="Thumbs.db" server="C:/xampp/htdocs/brasfoot/" local="130969949523587472" remote="130969949520000000" Dst="2" />
<file name="AlphaBar.png" server="C:/xampp/htdocs/" local="130969949520000000" remote="130969949520000000" Dst="2" />
<file name="bar-opacity.png" server="C:/xampp/htdocs/" local="130969949520000000" remote="130969949520000000" Dst="2" />
<file name="Bars.png" server="C:/xampp/htdocs/" local="130969949520000000" remote="130969949520000000" Dst="2" />
<file name="map-opacity.png" server="C:/xampp/htdocs/" local="130969949520000000" remote="130969949520000000" Dst="2" />
<file name="mappoint.gif" server="C:/xampp/htdocs/" local="130969949520000000" remote="130969949520000000" Dst="2" />
<file name="Maps.png" server="C:/xampp/htdocs/" local="130969949520000000" remote="130969949520000000" Dst="2" />
<file name="NoColor.png" server="C:/xampp/htdocs/" local="130969949520000000" remote="130969949520000000" Dst="2" />
<file name="picker.gif" server="C:/xampp/htdocs/" local="130969949520000000" remote="130969949520000000" Dst="2" />
<file name="preview-opacity.png" server="C:/xampp/htdocs/" local="130969949520000000" remote="130969949520000000" Dst="2" />
<file name="rangearrows.gif" server="C:/xampp/htdocs/" local="130969949520000000" remote="130969949520000000" Dst="2" />
<file name="Thumbs.db" server="C:/xampp/htdocs/" local="130969949523587472" remote="130969949520000000" Dst="2" />
</dwsync>